{"mood": "neutral", "status": "active", "plans": [{"plan": "Continue exploring more anime series like Attack on Titan", "start_date": "2024-12-26", "priority": "high"}, {"plan": "Integrate more yoga and meditation into my routine", "start_date": "2024-12-30", "priority": "medium"}, {"plan": "Organize a group meditation walk with friends to share the experience", "start_date": "2025-01-13", "priority": "low"}, {"plan": "Explore more plant-based recipes, inviting friends for a cooking session", "start_date": "2024-12-24", "priority": "high"}, {"plan": "Curate a high-energy playlist for music passion", "start_date": "2024-12-25", "priority": "high"}, {"plan": "Continue reflective journaling practice and experiment with new creative outlets", "start_date": "2024-12-26", "priority": "medium"}, {"plan": "Experiment with dance or art as a creative outlet to express evolving sense of self", "start_date": "2024-12-27", "priority": "medium"}, {"plan": "Share EDM playlist with a wider audience", "start_date": "2024-12-24", "priority": "high"}, {"plan": "Engage in a collaborative art project with friends", "start_date": "2024-12-24", "priority": "high"}, {"plan": "Explore more guided meditations", "start_date": "2024-12-26", "priority": "medium"}, {"plan": "Continue practicing aerial yoga and explore more neon-themed workouts.", "start_date": "2024-12-26", "priority": "high"}, {"plan": "Experiment with more creative superfood recipes.", "start_date": "2024-12-27", "priority": "medium"}, {"plan": "Explore new anime series with similar high-energy vibes.", "start_date": "2024-12-26", "priority": "high"}, {"plan": "Organize a digital art jam with friends.", "start_date": "2025-01-10", "priority": "medium"}, {"plan": "Explore more digital painting techniques", "start_date": "2024-12-24", "priority": "high"}, {"plan": "Continue Pilates journey", "start_date": "2024-12-24", "priority": "high"}, {"plan": "Watch evening of nature documentaries", "start_date": "2024-12-24", "priority": "high"}]}